nvdbapiv3/__init__.py
nvdbapiv3/apiforbindelse.py
nvdbapiv3/nvdbapiv3.py
nvdbapi_v3-1.0.0.dist-info/LICENSE
nvdbapi_v3-1.0.0.dist-info/WHEEL
nvdbapi_v3-1.0.0.dist-info/METADATA
nvdbapi_v3-1.0.0.dist-info/RECORD
