Metadata-Version: 2.1
Name: nvdbapi-v3
Version: 1.0.0
Summary: "Read data from Norwegian government road database NVDB api https://nvdbapiles-v3.atlas.vegvesen.no/dokumentasjon"
Home-page: https://github.com/LtGlahn/nvdbapi-V3
License: MIT
Author: LtGlahn
Author-email: jensen72@gmail.com
Requires-Python: >=3.7,<4.0
Classifier: Development Status :: 5 - Production/Stable
Classifier: Environment :: Console
Classifier: License :: OSI Approved :: MIT License
Classifier: Operating System :: OS Independent
Classifier: Programming Language :: Python :: 3
Classifier: Programming Language :: Python :: 3.10
Classifier: Programming Language :: Python :: 3.7
Classifier: Programming Language :: Python :: 3.8
Classifier: Programming Language :: Python :: 3.9
Classifier: Topic :: Scientific/Engineering :: GIS
Classifier: Topic :: Scientific/Engineering :: Information Analysis
Classifier: Topic :: Software Development :: Documentation
Classifier: Topic :: Software Development :: Libraries :: Python Modules
Requires-Dist: python-dateutil (>=2.8,<3.0)
Requires-Dist: requests (>=2.28,<3.0)
Requires-Dist: urllib3 (>=1.26.4,<2.0.0)
Project-URL: Repository, https://github.com/LtGlahn/nvdbapi-V3
